CHANGES.txt
LICENSE.txt
README.txt
bootstrap.py
buildout.cfg
setup.py
src/getpaid/__init__.py
src/getpaid.authorizedotnet.egg-info/PKG-INFO
src/getpaid.authorizedotnet.egg-info/SOURCES.txt
src/getpaid.authorizedotnet.egg-info/dependency_links.txt
src/getpaid.authorizedotnet.egg-info/namespace_packages.txt
src/getpaid.authorizedotnet.egg-info/not-zip-safe
src/getpaid.authorizedotnet.egg-info/requires.txt
src/getpaid.authorizedotnet.egg-info/top_level.txt
src/getpaid/authorizedotnet/__init__.py
src/getpaid/authorizedotnet/authorizenet.py
src/getpaid/authorizedotnet/authorizenet.txt
src/getpaid/authorizedotnet/certs.pem
src/getpaid/authorizedotnet/configure.zcml
src/getpaid/authorizedotnet/interfaces.py
src/getpaid/authorizedotnet/patch.py
src/getpaid/authorizedotnet/subscription.py
src/getpaid/authorizedotnet/subscription.txt
src/getpaid/authorizedotnet/tests.py