Metadata-Version: 1.0
Name: getpaid.authorizedotnet
Version: 0.6.3
Summary: GetPaid authorize.net payment processor functionality
Home-page: http://code.google.com/p/getpaid
Author: getpaid community
Author-email: getpaid-dev@googlegroups.com
License: ZPL2.1
Platform: UNKNOWN
Classifier: Framework :: Plone
Classifier: Framework :: Zope3
Classifier: Programming Language :: Python
Classifier: Intended Audience :: Developers
Classifier: License :: OSI Approved :: Zope Public License
Classifier: Operating System :: OS Independent
Classifier: Topic :: Office/Business :: Financial
Classifier: Topic :: Software Development :: Libraries
